{
    "last_update": 1747365903,
    "data": [
        {
            "display_name": "EthTrader",
            "limit": 5,
            "current": 5,
            "submissions": [
                "https://redd.it/1k5wynn",
                "https://redd.it/1kna9j7",
                "https://redd.it/1kmbsrr",
                "https://redd.it/1kllixb",
                "https://redd.it/1klj3x9"
            ],
            "community": "ethtrader"
        },
        {
            "display_name": "Airdrops",
            "limit": 2,
            "current": 0,
            "submissions": [],
            "community": "ethtrader"
        },
        {
            "display_name": "ETF",
            "limit": 2,
            "current": 1,
            "submissions": [
                "https://redd.it/1km9cae"
            ],
            "community": "ethtrader"
        },
        {
            "display_name": "SEC",
            "limit": 2,
            "current": 1,
            "submissions": [
                "https://redd.it/1kma80r"
            ],
            "community": "ethtrader"
        },
        {
            "display_name": "Chainlink",
            "limit": 2,
            "current": 1,
            "submissions": [
                "https://redd.it/1kmgpqt"
            ],
            "community": "ethtrader"
        },
        {
            "display_name": "Stables",
            "limit": 2,
            "current": 2,
            "submissions": [
                "https://redd.it/1klebyl",
                "https://redd.it/1klhrsu"
            ],
            "community": "ethtrader"
        },
        {
            "display_name": "Staking/Restaking",
            "limit": 2,
            "current": 0,
            "submissions": [],
            "community": "ethtrader"
        },
        {
            "display_name": "Wallets",
            "limit": 2,
            "current": 0,
            "submissions": [],
            "community": "ethtrader"
        },
        {
            "display_name": "Meme Coins",
            "limit": 2,
            "current": 1,
            "submissions": [
                "https://redd.it/1kmclr5"
            ],
            "community": "ethtrader"
        },
        {
            "display_name": "NFT",
            "limit": 2,
            "current": 1,
            "submissions": [
                "https://redd.it/1km8jek"
            ],
            "community": "ethtrader"
        },
        {
            "display_name": "Bridges",
            "limit": 2,
            "current": 0,
            "submissions": [],
            "community": "ethtrader"
        },
        {
            "display_name": "Politics",
            "limit": 2,
            "current": 0,
            "submissions": [],
            "community": "ethtrader"
        },
        {
            "display_name": "Influencers/Celebrities",
            "limit": 2,
            "current": 0,
            "submissions": [],
            "community": "ethtrader"
        },
        {
            "display_name": "Macroeconomics",
            "limit": 2,
            "current": 1,
            "submissions": [
                "https://redd.it/1kll7yw"
            ],
            "community": "ethtrader"
        },
        {
            "display_name": "Regulation",
            "limit": 2,
            "current": 0,
            "submissions": [],
            "community": "ethtrader"
        },
        {
            "display_name": "ETH Trading",
            "limit": 10,
            "current": 5,
            "submissions": [
                "https://redd.it/1kneksk",
                "https://redd.it/1kmxra8",
                "https://redd.it/1kmaj3p",
                "https://redd.it/1kldp2k",
                "https://redd.it/1klhhno"
            ],
            "community": "ethtrader"
        },
        {
            "display_name": "DeFi",
            "limit": 3,
            "current": 0,
            "submissions": [],
            "community": "ethtrader"
        },
        {
            "display_name": "Side Chains/Layer 2's",
            "limit": 8,
            "current": 3,
            "submissions": [
                "https://redd.it/1km43fw",
                "https://redd.it/1kll848",
                "https://redd.it/1klex6x"
            ],
            "community": "ethtrader"
        },
        {
            "display_name": "Exchanges",
            "limit": 2,
            "current": 0,
            "submissions": [],
            "community": "ethtrader"
        }
    ]
}